bchlib.cpython-310-x86_64-linux-gnu.so
bchlib-2.1.3.dist-info/COPYING
bchlib-2.1.3.dist-info/METADATA
bchlib-2.1.3.dist-info/top_level.txt
bchlib-2.1.3.dist-info/RECORD
bchlib-2.1.3.dist-info/WHEEL
