Metadata-Version: 2.1
Name: bchlib
Version: 2.1.3
Summary: A python wrapper module for the Linux kernel BCH library.
Home-page: https://github.com/jkent/python-bchlib
Author: Jeff Kent
Author-email: jeff@jkent.net
License: UNKNOWN
Platform: UNKNOWN
Classifier: License :: OSI Approved :: GNU General Public License v2 (GPLv2)
Classifier: Programming Language :: Python
Classifier: Programming Language :: Python :: 3
Classifier: Programming Language :: Python :: 3.6
Classifier: Programming Language :: Python :: Implementation :: CPython
Classifier: Programming Language :: Python :: Implementation :: PyPy
Classifier: Intended Audience :: Developers
Classifier: Topic :: Security :: Cryptography
Requires-Python: >=3.6.0
License-File: COPYING
